{
  "audiovisual_files": {
    "431490c6-cde9-4c01-a9c9-4f3e6ea7cc60": {
      "label": "Language_Austin_IS_06202024",
      "is_offline": false,
      "file_url": "https://ia800108.us.archive.org/31/items/is-06202024/IS_06202024.m4a",
      "duration": 1485,
      "caption_set": []
    }
  },
  "auto_generate_web_page": true,
  "description": [
    {
      "type": "paragraph",
      "children": [
        {
          "text": ""
        }
      ]
    }
  ],
  "citation": "",
  "item_type": "Audio",
  "label": "Language_Austin_IS_06202024",
  "created_at": "2025-02-13T14:29:58.120Z",
  "created_by": "JennSmith26",
  "updated_at": "2025-02-13T14:29:58.120Z",
  "updated_by": "JennSmith26"
}